jimeng_mcp/__init__.py
jimeng_mcp/server.py
iflow_mcp_wwwzhouhui_jimeng_mcp-0.1.0.dist-info/METADATA
iflow_mcp_wwwzhouhui_jimeng_mcp-0.1.0.dist-info/WHEEL
iflow_mcp_wwwzhouhui_jimeng_mcp-0.1.0.dist-info/entry_points.txt
iflow_mcp_wwwzhouhui_jimeng_mcp-0.1.0.dist-info/RECORD
