Metadata-Version: 2.4
Name: iflow-mcp_wwwzhouhui_jimeng-mcp
Version: 0.1.0
Summary: MCP server for JiMeng AI image and video generation
Author-email: Your Name <your.email@example.com>
Requires-Python: >=3.10
Requires-Dist: httpx-sse>=0.4
Requires-Dist: httpx>=0.27.0
Requires-Dist: mcp>=1.0.0
Requires-Dist: python-dotenv>=1.0.0
Requires-Dist: sse-starlette>=1.6.1
Requires-Dist: starlette>=0.37.0
Requires-Dist: uvicorn>=0.27.0
Provides-Extra: all
Requires-Dist: pytest-asyncio>=0.23.0; extra == 'all'
Requires-Dist: pytest>=8.0.0; extra == 'all'
Requires-Dist: starlette>=0.37.0; extra == 'all'
Requires-Dist: uvicorn>=0.27.0; extra == 'all'
Provides-Extra: dev
Requires-Dist: pytest-asyncio>=0.23.0; extra == 'dev'
Requires-Dist: pytest>=8.0.0; extra == 'dev'
Provides-Extra: http
Requires-Dist: starlette>=0.37.0; extra == 'http'
Requires-Dist: uvicorn>=0.27.0; extra == 'http'
Provides-Extra: sse
Requires-Dist: starlette>=0.37.0; extra == 'sse'
Requires-Dist: uvicorn>=0.27.0; extra == 'sse'
